{
  "settings": {
    "migrated": 4,
    "iconPacksPath": ".obsidian/icons",
    "fontSize": 16,
    "emojiStyle": "none",
    "iconColor": null,
    "recentlyUsedIcons": [
      "LiCalendarDays",
      "LiCode",
      "LiPanelBottomInactive",
      "LiCalendar",
      "LiCalendarX"
    ],
    "recentlyUsedIconsSize": 5,
    "rules": [],
    "extraMargin": {
      "top": 0,
      "right": 4,
      "bottom": 0,
      "left": 0
    },
    "iconInTabsEnabled": false,
    "iconInTitleEnabled": false,
    "iconInFrontmatterEnabled": false,
    "iconsBackgroundCheckEnabled": false,
    "iconsInNotesEnabled": true,
    "iconIdentifier": ":",
    "iconInFrontmatterFieldName": "icon",
    "iconColorInFrontmatterFieldName": "iconColor",
    "iconsInLinksEnabled": true,
    "debugMode": false
  },
  "Templates/2) Area": "LiArrowRightFromLine",
  "Templates/4) Archive": "LiArrowRightFromLine",
  "College": "LiSchool",
  "Home Page": "LiHome",
  "Notes": "LiStickyNote",
  "Templates": "LiFolders",
  "Other": "LiPanelBottomInactive",
  "Calendar": "LiCalendarDays",
  "Code": "LiCode"
}